pixelgreat/__init__.py
pixelgreat/constants.py
pixelgreat/core.py
pixelgreat/filters.py
pixelgreat/helpers.py
pixelgreat-1.4.2.dist-info/LICENSE
pixelgreat-1.4.2.dist-info/METADATA
pixelgreat-1.4.2.dist-info/WHEEL
pixelgreat-1.4.2.dist-info/entry_points.txt
pixelgreat-1.4.2.dist-info/top_level.txt
pixelgreat-1.4.2.dist-info/RECORD
