Metadata-Version: 2.1
Name: pixelgreat
Version: 1.4.2
Summary: A highly realistic RGB pixel filter
Author-email: Ella Jameson <ellagjameson@gmail.com>
License: GNU GENERAL PUBLIC LICENSE
Project-URL: homepage, https://github.com/nimaid/pixelgreat
Project-URL: repository, https://github.com/nimaid/pixelgreat
Project-URL: Issues, https://github.com/nimaid/pixelgreat/issues
Classifier: Topic :: Artistic Software
Classifier: Topic :: Multimedia :: Graphics
Classifier: Topic :: Multimedia :: Graphics :: Graphics Conversion
License-File: LICENSE
Requires-Dist: Pillow >10.0
